pytaxonomies/__init__.py
pytaxonomies/api.py
pytaxonomies/data/misp-taxonomies/CERT-XLM/machinetag.json
pytaxonomies/data/misp-taxonomies/DFRLab-dichotomies-of-disinformation/machinetag.json
pytaxonomies/data/misp-taxonomies/DML/machinetag.json
pytaxonomies/data/misp-taxonomies/GrayZone/machinetag.json
pytaxonomies/data/misp-taxonomies/MANIFEST.json
pytaxonomies/data/misp-taxonomies/PAP/machinetag.json
pytaxonomies/data/misp-taxonomies/access-method/machinetag.json
pytaxonomies/data/misp-taxonomies/accessnow/machinetag.json
pytaxonomies/data/misp-taxonomies/acs-marking/machinetag.json
pytaxonomies/data/misp-taxonomies/action-taken/machinetag.json
pytaxonomies/data/misp-taxonomies/admiralty-scale/machinetag.json
pytaxonomies/data/misp-taxonomies/adversary/machinetag.json
pytaxonomies/data/misp-taxonomies/ais-marking/machinetag.json
pytaxonomies/data/misp-taxonomies/analyst-assessment/machinetag.json
pytaxonomies/data/misp-taxonomies/approved-category-of-action/machinetag.json
pytaxonomies/data/misp-taxonomies/artificial-satellites/machinetag.json
pytaxonomies/data/misp-taxonomies/aviation/machinetag.json
pytaxonomies/data/misp-taxonomies/binary-class/machinetag.json
pytaxonomies/data/misp-taxonomies/cccs/machinetag.json
pytaxonomies/data/misp-taxonomies/circl/machinetag.json
pytaxonomies/data/misp-taxonomies/cnsd/machinetag.json
pytaxonomies/data/misp-taxonomies/coa/machinetag.json
pytaxonomies/data/misp-taxonomies/collaborative-intelligence/machinetag.json
pytaxonomies/data/misp-taxonomies/common-taxonomy/machinetag.json
pytaxonomies/data/misp-taxonomies/copine-scale/machinetag.json
pytaxonomies/data/misp-taxonomies/course-of-action/machinetag.json
pytaxonomies/data/misp-taxonomies/crowdsec/machinetag.json
pytaxonomies/data/misp-taxonomies/cryptocurrency-threat/machinetag.json
pytaxonomies/data/misp-taxonomies/csirt-americas/machinetag.json
pytaxonomies/data/misp-taxonomies/csirt_case_classification/machinetag.json
pytaxonomies-2.1.0.dist-info/LICENSE
pytaxonomies-2.1.0.dist-info/METADATA
pytaxonomies-2.1.0.dist-info/WHEEL
pytaxonomies-2.1.0.dist-info/entry_points.txt
pytaxonomies-2.1.0.dist-info/RECORD
