Metadata-Version: 2.3
Name: pytaxonomies
Version: 2.1.0
Summary: Python API for the taxonomies.
License: BSD-3-Clause
Author: Raphaël Vinot
Author-email: raphael.vinot@circl.lu
Requires-Python: >=3.9
Classifier: Development Status :: 5 - Production/Stable
Classifier: Environment :: Console
Classifier: Intended Audience :: Science/Research
Classifier: Intended Audience :: Telecommunications Industry
Classifier: License :: OSI Approved :: BSD License
Classifier: Programming Language :: Python :: 3
Classifier: Programming Language :: Python :: 3.9
Classifier: Programming Language :: Python :: 3.10
Classifier: Programming Language :: Python :: 3.11
Classifier: Programming Language :: Python :: 3.12
Classifier: Programming Language :: Python :: 3.13
Classifier: Topic :: Internet
Classifier: Topic :: Security
Provides-Extra: remote
Provides-Extra: webui
Requires-Dist: Flask (>=3.1.0) ; extra == "webui"
Requires-Dist: Flask-Bootstrap (>=3.3.7.1) ; extra == "webui"
Requires-Dist: Flask-WTF (>=1.2.2) ; extra == "webui"
Requires-Dist: flask-nav (>=0.6) ; extra == "webui"
Requires-Dist: requests (>=2.32.3) ; extra == "remote"
